dashboards/__init__.py
dashboards/apps.py
dashboards/config.py
dashboards/dashboard.py
dashboards/exceptions.py
dashboards/forms.py
dashboards/log.py
dashboards/permissions.py
dashboards/registry.py
dashboards/types.py
dashboards/urls.py
dashboards/utils.py
dashboards/views.py
dashboards/component/__init__.py
dashboards/component/base.py
dashboards/component/form.py
dashboards/component/layout.py
dashboards/component/map.py
dashboards/component/text.py
dashboards/component/chart/__init__.py
dashboards/component/chart/chart.py
dashboards/component/chart/serializers.py
dashboards/component/gauge/__init__.py
dashboards/component/gauge/gauge.py
dashboards/component/stat/__init__.py
dashboards/component/stat/serializers.py
dashboards/component/stat/stat.py
dashboards/component/table/__init__.py
dashboards/component/table/mixins.py
dashboards/component/table/serializers.py
dashboards/component/table/table.py
dashboards/menus/__init__.py
dashboards/menus/menu.py
dashboards/menus/registry.py
dashboards/meta/__init__.py
dashboards/static/dashboards/loading.svg
dashboards/static/dashboards/css/dashboards.css
dashboards/static/dashboards/css/src/buttons.css
dashboards/static/dashboards/css/src/cards.css
dashboards/static/dashboards/css/src/dashboards.css
dashboards/static/dashboards/css/src/forms.css
dashboards/static/dashboards/css/src/gauge.css
dashboards/static/dashboards/css/src/grid.css
dashboards/static/dashboards/css/src/index.css
dashboards/static/dashboards/css/src/layout.css
dashboards/static/dashboards/css/src/menu.css
dashboards/static/dashboards/css/src/stat.css
dashboards/static/dashboards/css/src/theme.css
dashboards/static/dashboards/js/dashboard.js
dashboards/static/dashboards/js/icons.js
dashboards/static/dashboards/vendor/css/datatables.min.css
dashboards/static/dashboards/vendor/js/alpine.min.js
dashboards/static/dashboards/vendor/js/datatables.min.js
dashboards/static/dashboards/vendor/js/gauge.min.js
dashboards/static/dashboards/vendor/js/htmx.min.js
django_dashboards-0.1.7.dist-info/LICENSE
django_dashboards-0.1.7.dist-info/METADATA
django_dashboards-0.1.7.dist-info/WHEEL
django_dashboards-0.1.7.dist-info/top_level.txt
django_dashboards-0.1.7.dist-info/RECORD
