Metadata-Version: 2.1
Name: django-dashboards
Version: 0.1.7
Summary: Tools for building data dashboards with Django
Home-page: https://github.com/wildfish/django-dashboards
Author: Wildfish
Author-email: developers@wildfish.com
License: BSD-3-Clause
Platform: UNKNOWN
Classifier: Development Status :: 4 - Beta
Classifier: Environment :: Web Environment
Classifier: Intended Audience :: Developers
Classifier: License :: OSI Approved :: BSD License
Classifier: Operating System :: OS Independent
Classifier: Programming Language :: Python :: 3
Classifier: Programming Language :: Python :: 3.9
Classifier: Programming Language :: Python :: 3.10
Classifier: Programming Language :: Python :: 3.11
Classifier: Programming Language :: Python :: 3.12
Classifier: Framework :: Django
Classifier: Framework :: Django :: 3.2
Classifier: Framework :: Django :: 4.0
Classifier: Framework :: Django :: 4.1
Classifier: Framework :: Django :: 4.2
Requires-Python: >=3.9
License-File: LICENSE
Requires-Dist: Django >=3.2
Requires-Dist: django-cors-headers
Requires-Dist: django-asset-definitions
Requires-Dist: pandas
Requires-Dist: plotly
Requires-Dist: plotly-express
Requires-Dist: typing-extensions
